{
  "name": "hermes-doctor-plugins",
  "description": "Marketplace for installing hermes-doctor and related Hermes Agent plugins.",
  "owner": {
    "name": "AtomCollide-AI-陈宇锋团队"
  },
  "plugins": [
    {
      "name": "hermes-doctor",
      "description": "Hermes Agent 自诊断与安全自愈插件。",
      "version": "0.1.3",
      "author": {
        "name": "AtomCollide-AI-陈宇锋团队"
      },
      "source": "./hermes-doctor",
      "category": "developer-tools",
      "homepage": "https://github.com/AtomCollide-AI/hermes-doctor"
    }
  ]
}
